verysimplemodule/__init__.py
verysimplemodule/add.py
verysimplemodule/subtract.py
verysimplemodule/extras/__init__.py
verysimplemodule/extras/divide.py
verysimplemodule/extras/multiply.py
verysimplemodulesimple/__init__.py
verysimplemodulesimple/add.py
verysimplemodulesimple/subtract.py
verysimplemodulesimple/extras/__init__.py
verysimplemodulesimple/extras/divide.py
verysimplemodulesimple/extras/multiply.py
verysimplemodulesimple-0.0.4.dist-info/METADATA
verysimplemodulesimple-0.0.4.dist-info/WHEEL
verysimplemodulesimple-0.0.4.dist-info/top_level.txt
verysimplemodulesimple-0.0.4.dist-info/RECORD
